Metadata-Version: 2.1
Name: django-compress-staticfiles
Version: 1.0.1b0
Summary: A static files storage backend for compression using GZip and/or Brotli that inherits from Djangos ManifestFilesMixin and StaticFilesStorage; also minifies static files.
Home-page: https://github.com/armandtvz/django-compress-staticfiles
Author: Armandt van Zyl
Author-email: armandtvz@gmail.com
License: GPL-3.0
Platform: UNKNOWN
Classifier: Development Status :: 4 - Beta
Classifier: Environment :: Web Environment
Classifier: Framework :: Django
Classifier: Framework :: Django :: 2.2
Classifier: Framework :: Django :: 3.0
Classifier: Intended Audience :: Developers
Classifier: License :: OSI Approved :: GNU General Public License v3 (GPLv3)
Classifier: Operating System :: OS Independent
Classifier: Programming Language :: Python
Classifier: Programming Language :: Python :: 3
Classifier: Programming Language :: Python :: 3.5
Classifier: Programming Language :: Python :: 3.6
Classifier: Programming Language :: Python :: 3.7
Classifier: Programming Language :: Python :: 3.8
Classifier: Programming Language :: Python :: 3 :: Only
Classifier: Topic :: Internet :: WWW/HTTP
Requires-Python: >=3.5
